automl/__init__.py
automl/core.py
automl/data_analyzer.py
automl/feature_engineer.py
automl/model_selector.py
automl/py.typed
automl/utils.py
smartml_auto-1.0.0.dist-info/licenses/LICENSE
smartml_auto-1.0.0.dist-info/METADATA
smartml_auto-1.0.0.dist-info/WHEEL
smartml_auto-1.0.0.dist-info/top_level.txt
smartml_auto-1.0.0.dist-info/RECORD
